jaz/__init__.py
jaz/_cli.py
jaz/_filters.py
jaz/_globals.py
jaz/api.py
jaz/api.py.orig
jaz-0.2.0.dist-info/LICENSE
jaz-0.2.0.dist-info/METADATA
jaz-0.2.0.dist-info/WHEEL
jaz-0.2.0.dist-info/entry_points.txt
jaz-0.2.0.dist-info/RECORD
