Metadata-Version: 2.1
Name: jaz
Version: 0.2.0
Summary: Render jinja templates from the CLI
Author: Panos Mavrogiorgos
Author-email: pmav99@gmail.com
Requires-Python: >=3.8
Classifier: Programming Language :: Python :: 3
Classifier: Programming Language :: Python :: 3.8
Classifier: Programming Language :: Python :: 3.9
Classifier: Programming Language :: Python :: 3.10
Classifier: Programming Language :: Python :: 3.11
Provides-Extra: ansible
Requires-Dist: ansible ; extra == "ansible"
Requires-Dist: jinja2 (>=3.0)
Requires-Dist: typer[all] (>=0.9)
